arkas/__init__.py
arkas/analyzer/__init__.py
arkas/analyzer/accuracy.py
arkas/analyzer/balanced_accuracy.py
arkas/analyzer/base.py
arkas/analyzer/column_cooccurrence.py
arkas/analyzer/column_correlation.py
arkas/analyzer/columns.py
arkas/analyzer/content.py
arkas/analyzer/continuous_column.py
arkas/analyzer/correlation.py
arkas/analyzer/hexbin_column.py
arkas/analyzer/lazy.py
arkas/analyzer/mapping.py
arkas/analyzer/null_value.py
arkas/analyzer/numeric_summary.py
arkas/analyzer/plot_column.py
arkas/analyzer/scatter_column.py
arkas/analyzer/summary.py
arkas/analyzer/temporal_null_value.py
arkas/analyzer/temporal_plot_column.py
arkas/analyzer/transform.py
arkas/cli/__init__.py
arkas/cli/run.py
arkas/cli/utils.py
arkas/content/__init__.py
arkas/content/accuracy.py
arkas/content/balanced_accuracy.py
arkas/content/base.py
arkas/content/column_cooccurrence.py
arkas/content/column_correlation.py
arkas/content/continuous_series.py
arkas/content/correlation.py
arkas/content/hexbin_column.py
arkas/content/mapping.py
arkas/content/null_value.py
arkas/content/numeric_summary.py
arkas/content/plot_column.py
arkas/content/scatter_column.py
arkas/content/section.py
arkas/content/summary.py
arkas/content/temporal_null_value.py
arkas/content/temporal_plot_column.py
arkas/content/utils.py
arkas/content/vanilla.py
arkas/evaluator/__init__.py
arkas/evaluator/accuracy.py
arkas/evaluator/ap.py
arkas/evaluator/balanced_accuracy.py
arkas/evaluator/base.py
arkas/evaluator/binary_ap.py
arkas/evaluator/binary_classification.py
arkas/evaluator/binary_confmat.py
arkas/evaluator/binary_fbeta.py
arkas/evaluator/binary_jaccard.py
arkas/evaluator/binary_precision.py
arkas/evaluator/binary_recall.py
arkas/evaluator/binary_roc_auc.py
arkas/evaluator/energy.py
arkas/evaluator/jensen_shannon.py
arkas/evaluator/kl.py
arkas/evaluator/lazy.py
arkas/evaluator/mae.py
arkas/evaluator/mape.py
arkas/evaluator/mapping.py
arkas/evaluator/median_error.py
arkas/evaluator/mse.py
arkas/evaluator/msle.py
arkas-0.0.1a15.dist-info/LICENSE
arkas-0.0.1a15.dist-info/METADATA
arkas-0.0.1a15.dist-info/WHEEL
arkas-0.0.1a15.dist-info/RECORD
