Metadata-Version: 2.3
Name: arkas
Version: 0.0.1a15
Summary: Library to evaluate ML model performances
License: BSD-3-Clause
Keywords: ML model,evaluation,classification,regression
Author: Thibaut Durand
Author-email: durand.tibo+gh@gmail.com
Requires-Python: >=3.9,<3.13
Classifier: Development Status :: 3 - Alpha
Classifier: Intended Audience :: Developers
Classifier: Intended Audience :: Information Technology
Classifier: Intended Audience :: Science/Research
Classifier: License :: OSI Approved :: BSD License
Classifier: Operating System :: POSIX :: Linux
Classifier: Programming Language :: Python :: 3
Classifier: Programming Language :: Python :: 3.9
Classifier: Programming Language :: Python :: 3.10
Classifier: Programming Language :: Python :: 3.11
Classifier: Programming Language :: Python :: 3.12
Classifier: Topic :: Scientific/Engineering
Classifier: Topic :: Scientific/Engineering :: Artificial Intelligence
Classifier: Topic :: Software Development :: Libraries
Provides-Extra: all
Provides-Extra: cli
Requires-Dist: colorlog (>=6.7,<7.0) ; extra == "all" or extra == "cli"
Requires-Dist: coola (>=0.8.2,<1.0)
Requires-Dist: grizz (>=0.2.0a17,<1.0)
Requires-Dist: hya (>=0.2,<1.0) ; extra == "all" or extra == "cli"
Requires-Dist: hydra-core (>=1.3,<2.0) ; extra == "all" or extra == "cli"
Requires-Dist: iden (>=0.1.1a0,<1.0)
Requires-Dist: jinja2 (>=3.0,<4.0)
Requires-Dist: markdown (>=3.4,<4.0) ; extra == "all"
Requires-Dist: matplotlib (>=3.6,<4.0)
Requires-Dist: numpy (>=1.22,<3.0)
Requires-Dist: objectory (>=0.2,<1.0)
Requires-Dist: omegaconf (>=2.1,<3.0) ; extra == "all" or extra == "cli"
Requires-Dist: plotly (>=5.24.0,<6.0) ; extra == "all"
Requires-Dist: polars (>=1.0,<2.0)
Requires-Dist: scikit-learn (>=1.3,<2.0)
Requires-Dist: scipy (>=1.10,<2.0) ; extra == "all"
Requires-Dist: tqdm (>=4.65,<5.0) ; extra == "all"
Project-URL: Homepage, https://github.com/durandtibo/arkas
Project-URL: Repository, https://github.com/durandtibo/arkas
